{
  "10:1": {"leaf":504,"lines":[
    ["And these [are] the generations",2],
    ["of the sons of Noah:",2],
    ["Shem, Ham, and Japheth;",3],
    ["and to them were sons born",3],
    ["after the flood.",2]
  ]},
  "10:2": {"leaf":504,"lines":[
    ["The sons of Japheth:",2],
    ["Gomer, and Magog, and Madai,",3],
    ["and Javan, and Tubal,",2],
    ["and Meshech, and Tiras.",2]
  ]},
  "10:3": {"leaf":504,"lines":[
    ["And the sons of Gomer:",2],
    ["Ashkenaz, and Riphath,",2],
    ["and Togarmah.",1]
  ]},
  "10:4": {"leaf":504,"lines":[
    ["And the sons of Javan:",2],
    ["Elishah, and Tarshish,",2],
    ["[the] Kittim, and [the] Dodanim.",2]
  ]},
  "10:5": {"leaf":504,"lines":[
    ["Of these were separated",2],
    ["the isles of the nations",2],
    ["in their lands,",1],
    ["every one after his tongue;",2],
    ["after their families,",1],
    ["in their nations.",1]
  ]},
  "10:6": {"leaf":504,"lines":[
    ["And the sons of Ham:",2],
    ["Cush, and Mizraim,",2],
    ["and Put, and Canaan.",2]
  ]},
  "10:7": {"leaf":504,"lines":[
    ["And the sons of Cush:",2],
    ["Seba, and Havilah, and Sabtah,",3],
    ["and Raamah, and Sabteca:",2],
    ["and the sons of Raamah:",2],
    ["Sheba and Dedan.",2]
  ]},
  "10:8": {"leaf":504,"lines":[
    ["And Cush ¹begat Nimrod;",4],
    ["he began",2],
    ["to be a ²hero on the earth.",3]
  ],"footnotes":{"1":"H. bore","2":"Or. mighty man"}},
  "10:9": {"leaf":504,"lines":[
    ["He was",2],
    ["a ²hero of hunting",2],
    ["before the Lord,",2],
    ["therefore it is said:",3],
    ["Like Nimrod",1],
    ["a ²hero of hunting",2],
    ["before the Lord.",2]
  ]},
  "10:10": {"leaf":504,"lines":[
    ["And it was",1],
    ["the beginning of his kingdom:",2],
    ["Babel, and Erech,",2],
    ["and Accad, and Calneh,",2],
    ["in the land Shinar.",2]
  ]},
  "10:11": {"leaf":504,"lines":[
    ["From that land",3],
    ["he went out [to] Assyria,³",2],
    ["and built Nineveh",3],
    ["and ⁴Rehoboth-Ir,",3],
    ["and Calah,",2]
  ],"footnotes":{"3":"Or. went out Asshur","4":"Or. Rehoboth, Ir. Or, the city of Rehoboth"}},
  "10:12": {"leaf":504,"lines":[
    ["And Resen",2],
    ["between Nineveh and (between) Calah.",4],
    ["that [is] the great city.",3]
  ]},
  "10:13": {"leaf":504,"lines":[
    ["And Mizraim ¹begat",2],
    ["[the] Ludim,",2],
    ["and [the] Anamim,",2],
    ["and [the] Lehabim,",2],
    ["and [the] Naphtuhim,",2]
  ]},
  "10:14": {"leaf":504,"lines":[
    ["And [the] Pathrusim,",2],
    ["and [the] Casluhim,",2],
    ["⁵whence went forth [the] Philistines,",4],
    ["and [the] Caphtorim.",2]
  ],"footnotes":{"5":"Or. out of whom"}},
  "10:15": {"leaf":504,"lines":[
    ["And Canaan ¹begat",2],
    ["Zidon his first-born,",3],
    ["and Heth;",2]
  ]},
  "10:16": {"leaf":504,"lines":[
    ["And the Jebusite,",2],
    ["and the Amorite,",2],
    ["and the Girgashite,",2]
  ]},
  "10:17": {"leaf":504,"partial":"end-on-next","lines":[
    ["And the Hivite,",2],
    ["and the Arkite,",2]
  ]}
}
